lsstream/__init__.py
lsstream/defaults.py
lsstream/file_generation.py
lsstream/prompts.py
lsstream/run.py
lsstream/style.py
lsstream/test.py
lsstream-1.4.2.dist-info/LICENSE
lsstream-1.4.2.dist-info/METADATA
lsstream-1.4.2.dist-info/WHEEL
lsstream-1.4.2.dist-info/top_level.txt
lsstream-1.4.2.dist-info/RECORD
