Metadata-Version: 2.1
Name: lsstream
Version: 1.4.2
Summary: To help lazy tech boys and girls at ASU's SILC LSS with Streaming Requests 😴 🖥️ 🎞️
Author-email: Wermutton <redacted@redacted.redacted>
Project-URL: Homepage, https://github.com/Wermutton/lsstream
Project-URL: Bug Tracker, https://github.com/Wermutton/lsstream/issues
Classifier: Programming Language :: Python :: 3
Classifier: License :: OSI Approved :: MIT License
Classifier: Operating System :: OS Independent
Requires-Python: >=3.7
License-File: LICENSE
Requires-Dist: pyfiglet
Requires-Dist: pyperclip
Requires-Dist: termcolor
Requires-Dist: colorama
